Metadata-Version: 1.0
Name: eaven-distributions
Version: 0.2
Summary: Gaussian and Binomial distributions
Home-page: UNKNOWN
Author: Eaven Khaw
Author-email: cykhaw@hotmail.com
License: UNKNOWN
Platform: UNKNOWN
